sPyMem/__init__.py
sPyMem/CA3_content_addressable/CA3_content_addressable.py
sPyMem/CA3_content_addressable/__init__.py
sPyMem/CA3_content_addressable/config/network_config.json
sPyMem/ca3/CA3.py
sPyMem/ca3/__init__.py
sPyMem/ca3/config/network_config.json
sPyMem/hippocampus_bioinspired_dg_ca1/__init__.py
sPyMem/hippocampus_bioinspired_dg_ca1/ca1.py
sPyMem/hippocampus_bioinspired_dg_ca1/dg.py
sPyMem/hippocampus_bioinspired_dg_ca1/hippocampus_bioinspired_dg_ca1.py
sPyMem/hippocampus_bioinspired_dg_ca1/config/network_config.json
sPyMem/hippocampus_with_forgetting/__init__.py
sPyMem/hippocampus_with_forgetting/hippocampus_with_forgetting.py
sPyMem/hippocampus_with_forgetting/config/hippocampus_with_forgetting_network_config.json
sPyMem-0.0.8.dist-info/LICENSE
sPyMem-0.0.8.dist-info/METADATA
sPyMem-0.0.8.dist-info/WHEEL
sPyMem-0.0.8.dist-info/top_level.txt
sPyMem-0.0.8.dist-info/RECORD
