Metadata-Version: 2.1
Name: sPyMem
Version: 0.0.8
Summary: An open-source package that offer fully-functional spike-based bio-inspired hippocampal memory models implemented with SNN technology in the SpiNNaker hardware.
Home-page: https://github.com/dancasmor/sPyMem
Author: Daniel Casanueva Morato
Author-email: dcasanueva@us.es
Project-URL: Bug Tracker, https://github.com/dancasmor/sPyMem/issues
Classifier: Programming Language :: Python :: 3
Classifier: License :: OSI Approved :: GNU General Public License v3 (GPLv3)
Classifier: Operating System :: OS Independent
Requires-Python: >=3.6
License-File: LICENSE
